fitness_diet_tracker/__init__.py
fitness_diet_tracker/diet_package/__init__.py
fitness_diet_tracker/diet_package/dietoptions.py
fitness_diet_tracker/diet_package/planoptions.py
fitness_diet_tracker/diet_package/tempCodeRunnerFile.py
fitness_diet_tracker/workout_plan/__init__.py
fitness_diet_tracker/workout_plan/warmup.py
fitness_diet_tracker/workout_plan/workout.py
fitness_diet_tracker-0.0.1.dist-info/LICENSE.txt
fitness_diet_tracker-0.0.1.dist-info/METADATA
fitness_diet_tracker-0.0.1.dist-info/WHEEL
fitness_diet_tracker-0.0.1.dist-info/top_level.txt
fitness_diet_tracker-0.0.1.dist-info/RECORD
