Metadata-Version: 2.1
Name: fitness-diet-tracker
Version: 0.0.1
Summary: Fitness and Diet Tracker Package - DATA 533 Project
Author-email: Christopher Mulya <cprasetya2000@gmail.com>
Project-URL: Homepage, https://github.com/cmulya/533-Group14
Project-URL: Issues, https://github.com/cmulya/533-Group14/issues
Classifier: Programming Language :: Python :: 3
Classifier: License :: OSI Approved :: MIT License
Classifier: Operating System :: OS Independent
Requires-Python: >=3.8
License-File: LICENSE.txt
